dummy_python_cli/entry.py
dummy_python_cli-0.1.0.dist-info/entry_points.txt
dummy_python_cli-0.1.0.dist-info/LICENSE
dummy_python_cli-0.1.0.dist-info/WHEEL
dummy_python_cli-0.1.0.dist-info/METADATA
dummy_python_cli-0.1.0.dist-info/RECORD
